pybiopax/__init__.py
pybiopax/api.py
pybiopax/paths.py
pybiopax/pc_client.py
pybiopax/references.py
pybiopax/xml_util.py
pybiopax/biopax/__init__.py
pybiopax/biopax/base.py
pybiopax/biopax/interaction.py
pybiopax/biopax/model.py
pybiopax/biopax/physical_entity.py
pybiopax/biopax/util.py
pybiopax/tests/__init__.py
pybiopax/tests/test_biopax.py
pybiopax/tests/test_paths.py
pybiopax/tests/test_serialization.py
pybiopax-0.1.5.dist-info/LICENSE
pybiopax-0.1.5.dist-info/METADATA
pybiopax-0.1.5.dist-info/WHEEL
pybiopax-0.1.5.dist-info/top_level.txt
pybiopax-0.1.5.dist-info/RECORD
