Metadata-Version: 2.1
Name: pybiopax
Version: 0.1.5
Summary: A Python implementation of the BioPAX object model, and parts of PaxTools.
Home-page: https://github.com/indralab/pybiopax
Author: Benjamin M. Gyori, Harvard Medical School
Author-email: benjamin_gyori@hms.harvard.edu
Keywords: biology,pathway
Classifier: Development Status :: 4 - Beta
Classifier: Programming Language :: Python :: 3.6
Classifier: Programming Language :: Python :: 3.7
Classifier: Programming Language :: Python :: 3.8
Classifier: Programming Language :: Python :: 3.9
Classifier: License :: OSI Approved :: BSD License
License-File: LICENSE
Requires-Dist: lxml
Requires-Dist: requests
Requires-Dist: tqdm
